pytest_curio/__init__.py
pytest_curio/_version.py
pytest_curio/plugin.py
pytest_curio-1.1.0.dist-info/LICENSE
pytest_curio-1.1.0.dist-info/METADATA
pytest_curio-1.1.0.dist-info/WHEEL
pytest_curio-1.1.0.dist-info/entry_points.txt
pytest_curio-1.1.0.dist-info/top_level.txt
pytest_curio-1.1.0.dist-info/RECORD
