Metadata-Version: 2.1
Name: pytest-curio
Version: 1.1.0
Summary: Pytest support for curio.
Home-page: https://github.com/johnnoone/pytest-curio
Author: Xavier Barbosa
Author-email: clint.northwood@gmail.com
License: Apache License 2.0
Classifier: Intended Audience :: Developers
Classifier: Programming Language :: Python :: 3.9
Classifier: Programming Language :: Python :: 3.10
Classifier: Programming Language :: Python :: 3.11
Classifier: Topic :: Software Development :: Testing
License-File: LICENSE
Requires-Dist: pytest
Requires-Dist: curio
